neuroscope/__init__.py
neuroscope/__main__.py
neuroscope/__version__.py
neuroscope/diagnostics/__init__.py
neuroscope/diagnostics/posttraining.py
neuroscope/diagnostics/pretraining.py
neuroscope/diagnostics/training_monitors.py
neuroscope/mlp/__init__.py
neuroscope/mlp/activations.py
neuroscope/mlp/core.py
neuroscope/mlp/initializers.py
neuroscope/mlp/losses.py
neuroscope/mlp/metrics.py
neuroscope/mlp/mlp.py
neuroscope/mlp/optimizers.py
neuroscope/mlp/utils.py
neuroscope/py.typed
neuroscope/viz/__init__.py
neuroscope/viz/plots.py
neuroscope-0.2.2.dist-info/LICENSE
neuroscope-0.2.2.dist-info/METADATA
neuroscope-0.2.2.dist-info/WHEEL
neuroscope-0.2.2.dist-info/entry_points.txt
neuroscope-0.2.2.dist-info/RECORD
