Metadata-Version: 2.1
Name: neuroscope
Version: 0.2.2
Summary: A microscope for informed training of multi-layer perceptron, diagnosing training issues at granular level and accelerating learning and rapid prototyping.
Home-page: https://ahmadrazacdx.github.io/neuroscope/
License: Apache-2.0
Keywords: neural-networks,machine-learning,deep-learning,mlp,diagnostics,education,research
Author: Ahmad Raza
Author-email: ahmadrazacdx@gmail.com
Requires-Python: >=3.12,<4.0
Classifier: Development Status :: 5 - Production/Stable
Classifier: Environment :: Console
Classifier: Intended Audience :: Developers
Classifier: Intended Audience :: Education
Classifier: Intended Audience :: Science/Research
Classifier: License :: OSI Approved :: Apache Software License
Classifier: Natural Language :: English
Classifier: Operating System :: OS Independent
Classifier: Programming Language :: Python :: 3
Classifier: Programming Language :: Python :: 3.12
Classifier: Programming Language :: Python :: 3.11
Classifier: Topic :: Education
Classifier: Topic :: Scientific/Engineering :: Artificial Intelligence
Classifier: Topic :: Scientific/Engineering :: Information Analysis
Classifier: Topic :: Software Development :: Libraries :: Python Modules
Requires-Dist: matplotlib (>=3.5.0)
Requires-Dist: numpy (>=1.21.0)
Requires-Dist: wcwidth (>=0.2.0)
Project-URL: Changelog, https://github.com/ahmadrazacdx/neuroscope/releases
Project-URL: Documentation, https://ahmadrazacdx.github.io/neuroscope
Project-URL: Issues, https://github.com/ahmadrazacdx/neuro-scope/issues
Project-URL: Logo, https://raw.githubusercontent.com/ahmadrazacdx/neuro-scope/main/docs/_static/logo.webp
Project-URL: Repository, https://github.com/ahmadrazacdx/neuro-scope
Project-URL: Source, https://github.com/ahmadrazacdx/neuro-scope
